{
 "employees": [
  {
   "firstName": "drek",
   "lastName": "Doe",
   "scores": 80
  },
  {
   "firstName": "black",
   "lastName": "Smith",
   "scores": 100
  },
  {
   "firstName": "white",
   "lastName": "Jones",
   "scores": 10
  },
  {
   "firstName": "han",
   "lastName": "tan",
   "scores": 88
  },
  {
   "firstName": "han",
   "lastName": "tan",
   "scores": 88
  },
  {
   "firstName": "han",
   "lastName": "tan",
   "scores": 88
  },
  {
   "firstName": "han",
   "lastName": "tan",
   "scores": 88
  },
  {
   "firstName": "han",
   "lastName": "tan",
   "scores": 88
  }
 ]
}